{"2026-06-11":{"B200":{"od":4.38},"H200":{"od":3.75},"RTX_4090":{"od":0.46},"H100_SXM":{"od":2.44},"A100_SXM":{"od":1.07}},"2026-06-12":{"B200":{"od":4.38},"H200":{"od":3.69},"H100_SXM":{"od":2.61},"RTX_4090":{"od":0.46},"A100_SXM":{"od":1.09},"H100_PCIe":{"od":2.36}},"2026-06-15":{"RTX_5090":{"od":0.52,"spot":0.4,"n":39},"B200":{"od":4.38,"spot":2.81,"n":7},"H200":{"od":3.29,"spot":2.8,"n":7},"RTX_4090":{"od":0.54,"spot":0.35,"n":8},"H100_SXM":{"od":4,"spot":4,"n":0,"est":true},"A100_SXM":{"od":1.15,"spot":1.15,"n":0,"est":true}},"2026-03-18":{},"2026-03-19":{},"2026-03-20":{},"2026-03-21":{},"2026-03-22":{},"2026-03-23":{"B200":{"od":3.1,"spot":3.1,"n":0,"est":true},"H200":{"od":2.7,"spot":2.7,"n":0,"est":true}},"2026-03-24":{},"2026-03-25":{},"2026-03-26":{},"2026-03-27":{},"2026-03-28":{},"2026-03-29":{},"2026-03-30":{"B200":{"od":3.5,"spot":3.5,"n":0,"est":true},"H200":{"od":2.9,"spot":2.9,"n":0,"est":true}},"2026-03-31":{},"2026-04-01":{},"2026-04-02":{},"2026-04-03":{},"2026-04-04":{},"2026-04-05":{},"2026-04-06":{"B200":{"od":4.7,"spot":4.7,"n":0,"est":true},"H200":{"od":3.1,"spot":3.1,"n":0,"est":true}},"2026-04-07":{},"2026-04-08":{},"2026-04-09":{},"2026-04-10":{},"2026-04-11":{},"2026-04-12":{},"2026-04-13":{"B200":{"od":4.8,"spot":4.8,"n":0,"est":true},"H200":{"od":3.2,"spot":3.2,"n":0,"est":true},"H100_SXM":{"od":1.7,"spot":1.7,"n":0,"est":true},"A100_SXM":{"od":1,"spot":1,"n":0,"est":true},"RTX_5090":{"od":0.5,"spot":0.5,"n":0,"est":true}},"2026-04-14":{},"2026-04-15":{},"2026-04-16":{},"2026-04-17":{},"2026-04-18":{},"2026-04-19":{},"2026-04-20":{"B200":{"od":4.3,"spot":4.3,"n":0,"est":true},"H200":{"od":3,"spot":3,"n":0,"est":true},"H100_SXM":{"od":2,"spot":2,"n":0,"est":true},"A100_SXM":{"od":1,"spot":1,"n":0,"est":true},"RTX_5090":{"od":0.5,"spot":0.5,"n":0,"est":true}},"2026-04-21":{},"2026-04-22":{},"2026-04-23":{},"2026-04-24":{},"2026-04-25":{},"2026-04-26":{},"2026-04-27":{"B200":{"od":4.2,"spot":4.2,"n":0,"est":true},"H200":{"od":3.1,"spot":3.1,"n":0,"est":true},"H100_SXM":{"od":2.4,"spot":2.4,"n":0,"est":true},"A100_SXM":{"od":1.05,"spot":1.05,"n":0,"est":true},"RTX_5090":{"od":0.5,"spot":0.5,"n":0,"est":true}},"2026-04-28":{},"2026-04-29":{},"2026-04-30":{},"2026-05-01":{},"2026-05-02":{},"2026-05-03":{},"2026-05-04":{"B200":{"od":4.9,"spot":4.9,"n":0,"est":true},"H200":{"od":3.4,"spot":3.4,"n":0,"est":true},"H100_SXM":{"od":2.8,"spot":2.8,"n":0,"est":true},"A100_SXM":{"od":1.1,"spot":1.1,"n":0,"est":true},"RTX_5090":{"od":0.52,"spot":0.52,"n":0,"est":true}},"2026-05-05":{},"2026-05-06":{},"2026-05-07":{},"2026-05-08":{},"2026-05-09":{},"2026-05-10":{},"2026-05-11":{"B200":{"od":5.2,"spot":5.2,"n":0,"est":true},"H200":{"od":3.7,"spot":3.7,"n":0,"est":true},"H100_SXM":{"od":3.2,"spot":3.2,"n":0,"est":true},"A100_SXM":{"od":1.1,"spot":1.1,"n":0,"est":true},"RTX_5090":{"od":0.55,"spot":0.55,"n":0,"est":true}},"2026-05-12":{},"2026-05-13":{},"2026-05-14":{},"2026-05-15":{},"2026-05-16":{},"2026-05-17":{},"2026-05-18":{"B200":{"od":5,"spot":5,"n":0,"est":true},"H200":{"od":3.9,"spot":3.9,"n":0,"est":true},"H100_SXM":{"od":5.8,"spot":5.8,"n":0,"est":true},"A100_SXM":{"od":1.15,"spot":1.15,"n":0,"est":true},"RTX_5090":{"od":0.6,"spot":0.6,"n":0,"est":true}},"2026-05-19":{},"2026-05-20":{},"2026-05-21":{},"2026-05-22":{},"2026-05-23":{},"2026-05-24":{},"2026-05-25":{"B200":{"od":5.7,"spot":5.7,"n":0,"est":true},"H200":{"od":4.1,"spot":4.1,"n":0,"est":true},"H100_SXM":{"od":4.5,"spot":4.5,"n":0,"est":true},"A100_SXM":{"od":1.2,"spot":1.2,"n":0,"est":true},"RTX_5090":{"od":0.7,"spot":0.7,"n":0,"est":true}},"2026-05-26":{},"2026-05-27":{},"2026-05-28":{},"2026-05-29":{},"2026-05-30":{},"2026-05-31":{},"2026-06-01":{"B200":{"od":6.1,"spot":6.1,"n":0,"est":true},"H200":{"od":4.4,"spot":4.4,"n":0,"est":true},"H100_SXM":{"od":6.9,"spot":6.9,"n":0,"est":true},"A100_SXM":{"od":1.3,"spot":1.3,"n":0,"est":true},"RTX_5090":{"od":1.2,"spot":1.2,"n":0,"est":true}},"2026-06-02":{},"2026-06-03":{},"2026-06-04":{},"2026-06-05":{},"2026-06-06":{},"2026-06-07":{},"2026-06-08":{"B200":{"od":5.4,"spot":5.4,"n":0,"est":true},"H200":{"od":4.2,"spot":4.2,"n":0,"est":true},"H100_SXM":{"od":5.2,"spot":5.2,"n":0,"est":true},"A100_SXM":{"od":1.25,"spot":1.25,"n":0,"est":true},"RTX_5090":{"od":1,"spot":1,"n":0,"est":true}},"2026-06-09":{},"2026-06-10":{},"2026-06-13":{},"2026-06-14":{},"2026-06-16":{"RTX_5090":{"od":0.54,"spot":0.4,"n":42},"B200":{"od":4.38,"spot":3.74,"n":10},"H200":{"od":3.21,"spot":2.76,"n":7},"RTX_4090":{"od":0.54,"n":4}},"2026-06-17":{"RTX_5090":{"od":0.54,"spot":0.4,"n":41},"B200":{"od":4.38,"spot":2.81,"n":12},"H200":{"od":3.75,"spot":3.21,"n":6},"RTX_4090":{"od":0.51,"n":3},"H100_NVL":{"od":3,"n":2}},"2026-06-22":{"RTX_5090":{"od":0.53,"spot":0.37,"n":44},"B200":{"od":4.29,"spot":4.04,"n":6},"H100_NVL":{"od":2.27,"n":2},"H200":{"od":2.9,"n":3},"RTX_4090":{"od":0.54,"spot":0.39,"n":9},"H100_SXM":{"od":3.1,"spot":3.1,"n":0,"est":true},"A100_SXM":{"od":1.1,"spot":1.1,"n":0,"est":true}},"2026-06-23":{"RTX_5090":{"od":0.51,"spot":0.36,"n":45},"B200":{"od":4.38,"spot":4.22,"n":4},"H200":{"od":3.21,"n":3},"H100_SXM":{"od":2.34,"n":2},"H100_NVL":{"od":2.67,"n":2},"RTX_4090":{"od":0.54,"spot":0.27,"n":8}},"2026-07-02":{"RTX_5090":{"od":0.52,"spot":0.4,"n":40},"B200":{"od":5.88,"n":2},"H200":{"od":4.08,"n":3},"RTX_4090":{"od":0.4,"spot":0.33,"n":14},"H100_SXM":{"od":2.87,"n":2}},"2026-07-03":{"RTX_5090":{"od":0.54,"spot":0.4,"n":40},"B200":{"od":5.88,"n":3},"H200":{"od":3.29,"n":3},"RTX_4090":{"od":0.4,"spot":0.35,"n":16},"H100_NVL":{"od":2.14,"n":2}},"2026-07-04":{"RTX_5090":{"od":0.5,"spot":0.4,"n":47},"B200":{"od":5.88,"spot":4.63,"n":4},"H200":{"od":3.29,"n":3},"RTX_4090":{"od":0.57,"spot":0.35,"n":10}},"2026-07-05":{"RTX_5090":{"od":0.52,"spot":0.35,"n":49},"B200":{"od":5.88,"spot":4.38,"n":4},"RTX_4090":{"od":0.57,"spot":0.28,"n":9}},"2026-07-06":{"RTX_5090":{"od":0.47,"spot":0.33,"n":47},"H200":{"od":3.5,"n":2},"B200":{"od":5.88,"spot":4.63,"n":4},"RTX_4090":{"od":0.57,"spot":0.33,"n":7},"H100_SXM":{"od":2.27,"n":2},"A100_SXM":{"od":1,"spot":1,"n":0,"est":true}},"2026-07-07":{"RTX_5090":{"od":0.54,"spot":0.37,"n":47},"H200":{"od":3.35,"spot":3.03,"n":4},"RTX_4090":{"od":0.51,"spot":0.25,"n":11},"H100_SXM":{"od":2.27,"n":2}},"2026-07-08":{"RTX_5090":{"od":0.54,"spot":0.33,"n":46},"H200":{"od":3.53,"n":2},"RTX_4090":{"od":0.38,"spot":0.27,"n":12},"A100_PCIe":{"od":1,"n":2},"H100_SXM":{"od":2.27,"n":2}},"2026-07-09":{"RTX_5090":{"od":0.54,"spot":0.4,"n":44},"H200":{"od":3.41,"spot":3.29,"n":4},"H100_NVL":{"od":2.4,"spot":2,"n":3},"RTX_4090":{"od":0.4,"spot":0.33,"n":11},"H100_PCIe":{"od":1.74,"spot":1.6,"n":1},"H100_SXM":{"od":2.28,"n":1}},"2026-07-10":{"RTX_5090":{"od":0.52,"spot":0.4,"n":38},"H100_NVL":{"od":2.71,"spot":2.36,"n":2},"RTX_4090":{"od":0.39,"spot":0.33,"n":19},"H200":{"od":3.75,"spot":3.55,"n":1},"H100_SXM":{"od":2.33,"spot":2,"n":2},"A100_SXM":{"od":0.41,"spot":0.4,"n":1},"A100_PCIe":{"od":1,"n":1}},"2026-02-02":{"B200":{"od":2.2,"spot":2.2,"n":0,"est":true},"H200":{"od":2.2,"spot":2.2,"n":0,"est":true}},"2026-02-09":{"B200":{"od":2.3,"spot":2.3,"n":0,"est":true},"H200":{"od":2.2,"spot":2.2,"n":0,"est":true}},"2026-02-16":{"B200":{"od":2.6,"spot":2.6,"n":0,"est":true},"H200":{"od":2.3,"spot":2.3,"n":0,"est":true}},"2026-02-23":{"B200":{"od":2.8,"spot":2.8,"n":0,"est":true},"H200":{"od":2.4,"spot":2.4,"n":0,"est":true}},"2026-03-02":{"B200":{"od":3,"spot":3,"n":0,"est":true},"H200":{"od":2.5,"spot":2.5,"n":0,"est":true}},"2026-03-09":{"B200":{"od":2.9,"spot":2.9,"n":0,"est":true},"H200":{"od":2.5,"spot":2.5,"n":0,"est":true}},"2026-03-16":{"B200":{"od":2.7,"spot":2.7,"n":0,"est":true},"H200":{"od":2.6,"spot":2.6,"n":0,"est":true}},"2026-06-29":{"B200":{"od":3,"spot":3,"n":0,"est":true},"H200":{"od":3.2,"spot":3.2,"n":0,"est":true},"H100_SXM":{"od":2.9,"spot":2.9,"n":0,"est":true},"A100_SXM":{"od":1,"spot":1,"n":0,"est":true},"RTX_5090":{"od":0.55,"spot":0.55,"n":0,"est":true}},"2026-07-13":{"RTX_5090":{"od":0.47,"spot":0.33,"n":48},"RTX_4090":{"od":0.38,"spot":0.33,"n":11},"H200":{"od":4.08,"spot":3.82,"n":2},"H100_SXM":{"od":2.27,"spot":2,"n":2},"H100_NVL":{"od":2.83,"spot":0.8,"n":1}},"2026-07-14":{"RTX_5090":{"od":0.47,"spot":0.39,"n":45},"RTX_4090":{"od":0.39,"spot":0.33,"n":13},"H200":{"od":3.75,"spot":3.55,"n":4},"H100_PCIe":{"od":1.72,"n":1},"B200":{"od":6.88,"spot":5.63,"n":1}},"2026-07-15":{"H100_SXM":{"od":2.05,"spot":1.4,"n":9},"H100_PCIe":{"od":1.87,"spot":1.6,"n":1},"H100_NVL":{"od":2.07,"spot":1.97,"n":4},"H200":{"od":3.71,"spot":3.15,"n":3},"B200":{"od":7.51,"spot":6.88,"n":2},"A100_SXM":{"od":0.87,"spot":0.75,"n":21},"A100_PCIe":{"od":0.56,"spot":0.47,"n":19},"RTX_5090":{"od":0.48,"spot":0.33,"n":51},"RTX_4090":{"od":0.38,"spot":0.35,"n":56}}}